{
  "paths": {
    "/quizzes": {
      "post": {
        "description": "Sadece ADMIN ve TEACHER rolleri quiz oluşturabilir.",
        "operationId": "QuizzesController_create",
        "parameters": [],
        "requestBody": {
          "required": true,
          "content": {
            "application/json": {
              "schema": {
                "$ref": "#/components/schemas/CreateQuizDto"
              }
            }
          }
        },
        "responses": {
          "201": {
            "description": "Quiz başarıyla oluşturuldu."
          },
          "401": {
            "description": "Kimlik doğrulama gerekli - Bearer token eksik veya geçersiz."
          },
          "403": {
            "description": "Yetkisiz erişim - Sadece ADMIN ve TEACHER rolleri quiz oluşturabilir."
          }
        },
        "security": [
          {
            "bearer": []
          }
        ],
        "summary": "Yeni bir quiz oluştur",
        "tags": [
          "quizzes"
        ]
      },
      "get": {
        "description": "ADMIN, TEACHER ve STUDENT rolleri quizleri görüntüleyebilir.",
        "operationId": "QuizzesController_findAll",
        "parameters": [],
        "responses": {
          "200": {
            "description": "Tüm quizleri döndürür."
          },
          "401": {
            "description": "Kimlik doğrulama gerekli - Bearer token eksik veya geçersiz."
          }
        },
        "security": [
          {
            "bearer": []
          }
        ],
        "summary": "Tüm quizleri getir",
        "tags": [
          "quizzes"
        ]
      }
    },
    "/quizzes/{id}": {
      "get": {
        "description": "ADMIN, TEACHER ve STUDENT rolleri quiz detaylarını görüntüleyebilir.",
        "operationId": "QuizzesController_findOne",
        "parameters": [
          {
            "name": "id",
            "required": true,
            "in": "path",
            "schema": {
              "type": "string"
            }
          }
        ],
        "responses": {
          "200": {
            "description": "Tek bir quiz döndürür."
          },
          "401": {
            "description": "Kimlik doğrulama gerekli - Bearer token eksik veya geçersiz."
          },
          "404": {
            "description": "Quiz bulunamadı."
          }
        },
        "security": [
          {
            "bearer": []
          }
        ],
        "summary": "ID ile quiz getir",
        "tags": [
          "quizzes"
        ]
      },
      "patch": {
        "description": "Sadece ADMIN ve TEACHER rolleri quiz güncelleyebilir.",
        "operationId": "QuizzesController_update",
        "parameters": [
          {
            "name": "id",
            "required": true,
            "in": "path",
            "schema": {
              "type": "string"
            }
          }
        ],
        "requestBody": {
          "required": true,
          "content": {
            "application/json": {
              "schema": {
                "$ref": "#/components/schemas/UpdateQuizDto"
              }
            }
          }
        },
        "responses": {
          "200": {
            "description": "Quiz başarıyla güncellendi."
          },
          "401": {
            "description": "Kimlik doğrulama gerekli - Bearer token eksik veya geçersiz."
          },
          "403": {
            "description": "Yetkisiz erişim - Sadece ADMIN ve TEACHER rolleri quiz güncelleyebilir."
          },
          "404": {
            "description": "Quiz bulunamadı."
          }
        },
        "security": [
          {
            "bearer": []
          }
        ],
        "summary": "ID ile quiz güncelle",
        "tags": [
          "quizzes"
        ]
      },
      "delete": {
        "description": "Sadece ADMIN ve TEACHER rolleri quiz silebilir.",
        "operationId": "QuizzesController_remove",
        "parameters": [
          {
            "name": "id",
            "required": true,
            "in": "path",
            "schema": {
              "type": "string"
            }
          }
        ],
        "responses": {
          "204": {
            "description": "Quiz başarıyla silindi."
          },
          "401": {
            "description": "Kimlik doğrulama gerekli - Bearer token eksik veya geçersiz."
          },
          "403": {
            "description": "Yetkisiz erişim - Sadece ADMIN ve TEACHER rolleri quiz silebilir."
          },
          "404": {
            "description": "Quiz bulunamadı."
          }
        },
        "security": [
          {
            "bearer": []
          }
        ],
        "summary": "ID ile quiz sil",
        "tags": [
          "quizzes"
        ]
      }
    }
  },
  "components": {
    "schemas": {
      "CreateQuizDto": {
        "type": "object",
        "properties": {
          "lessonId": {
            "type": "string",
            "description": "ID of the lesson this quiz belongs to (optional)"
          },
          "title": {
            "type": "string",
            "description": "Title of the quiz"
          },
          "description": {
            "type": "string",
            "description": "Description of the quiz"
          },
          "subject": {
            "type": "string",
            "description": "Subject of the quiz"
          },
          "topic": {
            "type": "string",
            "description": "Topic of the quiz"
          },
          "difficulty": {
            "type": "string",
            "description": "Difficulty level of the quiz"
          },
          "quizType": {
            "type": "string",
            "enum": [
              "MULTIPLE_CHOICE",
              "OPEN_ENDED",
              "DRAG_DROP"
            ],
            "description": "Type of quiz (e.g., MULTIPLE_CHOICE, OPEN_ENDED)"
          },
          "questionCount": {
            "type": "number",
            "description": "Number of questions in the quiz"
          },
          "passingScore": {
            "type": "number",
            "description": "Passing score for the quiz (percentage)"
          },
          "questions": {
            "type": "object",
            "description": "JSON array of question objects"
          }
        },
        "required": [
          "title",
          "subject",
          "difficulty",
          "quizType",
          "questionCount",
          "passingScore",
          "questions"
        ]
      },
      "UpdateQuizDto": {
        "type": "object",
        "properties": {
          "lessonId": {
            "type": "string",
            "description": "ID of the lesson this quiz belongs to (optional)"
          },
          "title": {
            "type": "string",
            "description": "Title of the quiz"
          },
          "description": {
            "type": "string",
            "description": "Description of the quiz"
          },
          "subject": {
            "type": "string",
            "description": "Subject of the quiz"
          },
          "topic": {
            "type": "string",
            "description": "Topic of the quiz"
          },
          "difficulty": {
            "type": "string",
            "description": "Difficulty level of the quiz"
          },
          "quizType": {
            "type": "string",
            "enum": [
              "MULTIPLE_CHOICE",
              "OPEN_ENDED",
              "DRAG_DROP"
            ],
            "description": "Type of quiz (e.g., MULTIPLE_CHOICE, OPEN_ENDED)"
          },
          "questionCount": {
            "type": "number",
            "description": "Number of questions in the quiz"
          },
          "passingScore": {
            "type": "number",
            "description": "Passing score for the quiz (percentage)"
          },
          "questions": {
            "type": "object",
            "description": "JSON array of question objects"
          }
        }
      }
    }
  }
}